README.md
setup.py
seleniumbot/__init__.py
seleniumbot.egg-info/PKG-INFO
seleniumbot.egg-info/SOURCES.txt
seleniumbot.egg-info/dependency_links.txt
seleniumbot.egg-info/requires.txt
seleniumbot.egg-info/top_level.txt
seleniumbot/core/__init__.py
seleniumbot/core/action.py
seleniumbot/core/client.py
seleniumbot/core/seleniumbot.py
seleniumbot/utils/__init__.py
seleniumbot/utils/logger.py
seleniumbot/utils/randomizer.py