Metadata-Version: 2.1
Name: seleniumbot
Version: 0.0.2
Summary: SeleniumBot
Home-page: https://github.com/Mercurial5
Author: Mercurial5
Author-email: dias.nespayev@gmail.com
Keywords: SeleniumBot
Requires-Python: >=3.11
